ncl/__init__.py
ncl/__main__.py
ncl/abstractelement.py
ncl/abstractparam.py
ncl/action.py
ncl/area.py
ncl/assessment.py
ncl/assessmentstatement.py
ncl/attributeassessment.py
ncl/bind.py
ncl/body.py
ncl/causalconnector.py
ncl/compound.py
ncl/compoundaction.py
ncl/compoundcondition.py
ncl/compoundstatement.py
ncl/condition.py
ncl/connectorbase.py
ncl/connectorparam.py
ncl/connectorrole.py
ncl/descriptor.py
ncl/descriptorbase.py
ncl/head.py
ncl/link.py
ncl/media.py
ncl/param.py
ncl/port.py
ncl/property.py
ncl/region.py
ncl/regionbase.py
ncl/simple.py
ncl/simpleaction.py
ncl/simplecondition.py
ncl-0.0.1.dist-info/LICENSE
ncl-0.0.1.dist-info/METADATA
ncl-0.0.1.dist-info/WHEEL
ncl-0.0.1.dist-info/top_level.txt
ncl-0.0.1.dist-info/RECORD
