Metadata-Version: 2.1
Name: ncl
Version: 0.0.1
Summary: NCL Generator API has a main purpose facilitate NCL implementation using a Python language.
Home-page: https://github.com/MichaelBittencourt/NCL-Generator-API
Author: Michael Alves Bittencourt de Mello
Author-email: mchl.bittencourt@gmail.com
License: MIT License
